sqlIntuitive/__init__.py
sqlIntuitive/__main__.py
sqlIntuitive/conditionEnums.py
sqlIntuitive/dbSystems/__init__.py
sqlIntuitive/dbSystems/baseDbSystem.py
sqlIntuitive/dbSystems/mysqlSystem.py
sqlIntuitive/dbSystems/sqliteSystem.py
sqlIntuitive/dbSystems/supportTracker.py
sqlIntuitive/exceptions/__init__.py
sqlIntuitive/exceptions/baseException.py
sqlIntuitive/exceptions/adaptionProviderExceptions/__init__.py
sqlIntuitive/exceptions/adaptionProviderExceptions/baseException.py
sqlIntuitive/exceptions/adaptionProviderExceptions/subexceptions.py
sqlIntuitive/exceptions/conditionExceptions/__init__.py
sqlIntuitive/exceptions/conditionExceptions/baseException.py
sqlIntuitive/exceptions/conditionExceptions/subexceptions.py
sqlIntuitive/exceptions/other/__init__.py
sqlIntuitive/exceptions/parameterExceptions/__init__.py
sqlIntuitive/exceptions/parameterExceptions/baseException.py
sqlIntuitive/exceptions/parameterExceptions/subexceptions/__init__.py
sqlIntuitive/exceptions/parameterExceptions/subexceptions/other.py
sqlIntuitive/exceptions/parameterExceptions/subexceptions/invalidConstraintExceptions/__init__.py
sqlIntuitive/exceptions/parameterExceptions/subexceptions/invalidConstraintExceptions/baseException.py
sqlIntuitive/exceptions/parameterExceptions/subexceptions/invalidConstraintExceptions/subexceptions.py
sqlIntuitive/ext/__init__.py
sqlIntuitive/ext/customDataTypes.py
sqlIntuitive/sqlGeneration/__init__.py
sqlIntuitive/sqlGeneration/functionEnums.py
sqlIntuitive/sqlGeneration/mysql.py
sqlIntuitive/sqlGeneration/sqlite.py
sqlIntuitive/sqlGeneration/standard.py
sqlIntuitive-0.9.0.dist-info/LICENSE
sqlIntuitive-0.9.0.dist-info/METADATA
sqlIntuitive-0.9.0.dist-info/WHEEL
sqlIntuitive-0.9.0.dist-info/top_level.txt
sqlIntuitive-0.9.0.dist-info/RECORD
